present_cipher/__init__.py
present_cipher/present.py
present_cipher-1.0.0.dist-info/METADATA
present_cipher-1.0.0.dist-info/WHEEL
present_cipher-1.0.0.dist-info/top_level.txt
present_cipher-1.0.0.dist-info/RECORD
