Metadata-Version: 2.2
Name: present_cipher
Version: 1.0.0
Summary: A Python implementation of the PRESENT block cipher
Home-page: https://github.com/yourusername/present_cipher
Author: Your Name
Author-email: your.email@example.com
Classifier: Programming Language :: Python :: 3
Classifier: License :: OSI Approved :: MIT License
Classifier: Operating System :: OS Independent
Requires-Python: >=3.6
Dynamic: author
Dynamic: author-email
Dynamic: classifier
Dynamic: home-page
Dynamic: requires-python
Dynamic: summary
